openprattle/__init__.py
openprattle/babel.py
openprattle/log.py
openprattle/program.py
openprattle-1.1.2.dist-info/METADATA
openprattle-1.1.2.dist-info/WHEEL
openprattle-1.1.2.dist-info/entry_points.txt
openprattle-1.1.2.dist-info/licenses/LICENSE
openprattle-1.1.2.dist-info/RECORD
