Metadata-Version: 2.3
Name: openprattle
Version: 1.1.2
Summary: A convenience wrapper for seamlessly accessing the pybel library and obabel command-line tools
Project-URL: Homepage, https://github.com/Digichem-Project/openprattle
Project-URL: Issues, https://github.com/Digichem-Project/openprattle/issues
Author-email: "Oliver S. Lee" <osl@digi-chem.ac.uk>
License-File: LICENSE
Classifier: License :: OSI Approved :: GNU General Public License v2 (GPLv2)
Classifier: Operating System :: OS Independent
Classifier: Programming Language :: Python :: 3
Requires-Python: >=3.8
Requires-Dist: openbabel>=3.0.0
